sqlitewrapper/__init__.py
sqlitewrapper/databaseobjects.py
sqlitewrapper/datatypes.py
sqlitewrapper/errors.py
sqlitewrapper/examples/example.py
sqlitewrapper/examples/example_class.py
sqlitewrapper-0.1.6.dist-info/licenses/LICENSE
sqlitewrapper-0.1.6.dist-info/METADATA
sqlitewrapper-0.1.6.dist-info/WHEEL
sqlitewrapper-0.1.6.dist-info/top_level.txt
sqlitewrapper-0.1.6.dist-info/RECORD
