Metadata-Version: 2.4
Name: sqlitewrapper
Version: 0.1.6
Summary: A python object-oriented wrapper for sqlite
Author-email: Jude Cowden <jude.cowden@protonmail.com>
License-Expression: MIT
Project-URL: Homepage, https://github.com/judev1/sqlitewrapper
Project-URL: Repository, https://github.com/judev1/sqlitewrapper
Classifier: Programming Language :: Python :: 3
Classifier: Intended Audience :: Developers
Classifier: Topic :: Software Development :: Libraries
Requires-Python: >=3.7
License-File: LICENSE
Dynamic: license-file
